LICENSE
MANIFEST.in
README.md
requirements.txt
setup.py
loom/__init__.py
loom/app.py
loom/config.py
loom/decorators.py
loom/hosts.py
loom/puppet.py
loom/tasks.py
loom/utils.py
loom.egg-info/PKG-INFO
loom.egg-info/SOURCES.txt
loom.egg-info/dependency_links.txt
loom.egg-info/requires.txt
loom.egg-info/top_level.txt
loom/files/init/puppet.conf
loom/files/init/puppetmaster.conf
loom/files/puppet/auth.conf
loom/files/puppet/puppet.conf