Metadata-Version: 1.0
Name: loom
Version: 0.0.12
Summary: Elegant deployment with Fabric and Puppet.
Home-page: http://github.com/bfirsh/loom
Author: Ben Firshman
Author-email: ben@firshman.co.uk
License: UNKNOWN
Platform: UNKNOWN
